MANIFEST.in
distribute_setup.py
setup.py
ordrin/__init__.py
ordrin/api.py
ordrin/api_helper.py
ordrin/mutate.py
ordrin/schemas.json
ordrin.egg-info/PKG-INFO
ordrin.egg-info/SOURCES.txt
ordrin.egg-info/dependency_links.txt
ordrin.egg-info/requires.txt
ordrin.egg-info/top_level.txt