Metadata-Version: 1.1
Name: ordrin
Version: 1.0.5
Summary: Ordr.in API Client
Home-page: https://github.com/ordrin/api-py
Author: Ordr.in
Author-email: tech@ordr.in
License: UNKNOWN
Platform: UNKNOWN
Classifier: Programming Language :: Python
Classifier: Programming Language :: Python :: 2.7
Classifier: Operating System :: OS Independent
Classifier: Intended Audience :: Developers
Classifier: License :: OSI Approved :: Apache Software License
Classifier: Development Status :: 4 - Beta
Classifier: Topic :: Software Development
Classifier: Topic :: Internet
